tests/__init__.py
tests/test_custom_assertion.py
tests/test_custom_expected_conditions.py
tests/test_finder.py
tests/test_interactor.py
tests/test_interrogator.py
tests/test_page_element.py
tests/test_waiter.py
tests/unit_test_utils.py
tests/utilities/__init__.py
tests/utilities/test_attachments_api.py
tests/utilities/test_browser_handler.py
tests/utilities/test_config.py
tests/utilities/test_datetime_handler.py
tests/utilities/test_logger_handler.py
tests/utilities/test_string_util.py
uitestcore/__init__.py
uitestcore/custom_assertion.py
uitestcore/custom_expected_conditions.py
uitestcore/finder.py
uitestcore/interactor.py
uitestcore/interrogator.py
uitestcore/page.py
uitestcore/page_element.py
uitestcore/waiter.py
uitestcore/utilities/__init__.py
uitestcore/utilities/attachments_api.py
uitestcore/utilities/browser_handler.py
uitestcore/utilities/config_handler.py
uitestcore/utilities/datetime_handler.py
uitestcore/utilities/logger_handler.py
uitestcore/utilities/string_util.py
uitestcore-10.6.1.dist-info/LICENSE.md
uitestcore-10.6.1.dist-info/METADATA
uitestcore-10.6.1.dist-info/WHEEL
uitestcore-10.6.1.dist-info/top_level.txt
uitestcore-10.6.1.dist-info/RECORD
