Metadata-Version: 2.1
Name: uitestcore
Version: 10.6.1
Summary: Package providing common functionality for UI automation test packs
License: MIT
Classifier: Programming Language :: Python :: 3
Classifier: Operating System :: OS Independent
Classifier: License :: OSI Approved :: MIT License
License-File: LICENSE.md
Requires-Dist: certifi==2023.7.22
Requires-Dist: chardet==5.1.0
Requires-Dist: idna==3.4
Requires-Dist: pyhamcrest==2.0.4
Requires-Dist: python-dateutil==2.8.2
Requires-Dist: requests==2.31.0
Requires-Dist: selenium==4.11.2
Requires-Dist: six==1.16.0
Requires-Dist: urllib3==1.26.12
Requires-Dist: axe-selenium-python-nhsuk
